napari_subboxer/__init__.py
napari_subboxer/_version.py
napari_subboxer/cli.py
napari_subboxer/data_model.py
napari_subboxer/eralda.py
napari_subboxer/interactivity_utils.py
napari_subboxer/layer_utils.py
napari_subboxer/oriented_points_controls.py
napari_subboxer/plane_controls.py
napari_subboxer/points_controls.py
napari_subboxer/pose_io.py
napari_subboxer/subboxer.py
napari_subboxer/_qt/__init__.py
napari_subboxer/_qt/label_between_arrows.py
napari_subboxer/_qt/named_labeled_slider.py
napari_subboxer/_qt/open_close_buttons.py
napari_subboxer/_qt/selectable_button_list.py
napari_subboxer/_qt/subboxing_widget.py
napari_subboxer/_qt/typing.py
napari_subboxer/_qt/utils.py
napari_subboxer/_qt/tests/__init__.py
napari_subboxer/_qt/tests/test_label_between_arrows.py
napari_subboxer/_qt/tests/test_open_close_widget.py
napari_subboxer/_qt/tests/test_selectable_button_list.py
napari_subboxer-0.0.1.dist-info/LICENSE
napari_subboxer-0.0.1.dist-info/METADATA
napari_subboxer-0.0.1.dist-info/WHEEL
napari_subboxer-0.0.1.dist-info/entry_points.txt
napari_subboxer-0.0.1.dist-info/top_level.txt
napari_subboxer-0.0.1.dist-info/RECORD
