Metadata-Version: 2.1
Name: napari-subboxer
Version: 0.0.1
Summary: A napari plugin for interacting with electron cryotomograms
Home-page: https://github.com/alisterburt/napari-subboxer
Author: Alister Burt
Author-email: alisterburt@gmail.com
License: BSD-3-Clause
Project-URL: Bug Tracker, https://github.com/alisterburt/napari-subboxer/issues
Project-URL: Documentation, https://github.com/alisterburt/napari-subboxer#README.md
Project-URL: Source Code, https://github.com/alisterburt/napari-subboxer
Project-URL: User Support, https://github.com/alisterburt/napari-subboxer/issues
Platform: UNKNOWN
Classifier: Development Status :: 2 - Pre-Alpha
Classifier: Intended Audience :: Developers
Classifier: Framework :: napari
Classifier: Topic :: Software Development :: Testing
Classifier: Programming Language :: Python
Classifier: Programming Language :: Python :: 3
Classifier: Programming Language :: Python :: 3.7
Classifier: Programming Language :: Python :: 3.8
Classifier: Programming Language :: Python :: 3.9
Classifier: Operating System :: OS Independent
Classifier: License :: OSI Approved :: BSD License
Requires-Python: >=3.7
License-File: LICENSE
Requires-Dist: napari-plugin-engine (>=0.1.4)
Requires-Dist: numpy
Requires-Dist: napari[pyqt5] (==0.4.12)
Requires-Dist: mrcfile
Requires-Dist: typer
Requires-Dist: eulerangles
Requires-Dist: starfile
Requires-Dist: einops
Requires-Dist: pydantic
